<ui>
  <menubar>
    <menu name="File" action="FileAction">
      <placeholder name="FilePrintPlaceholder">
        <menuitem name="FileExportPDF" action="FilePrintPDFAction"/>
      </placeholder>
      <menu name="FileExport" action="FileExportAction">
        <placeholder name="FileExportPlaceholder">
          <menuitem name="FileReportExport" action="ReportExportAction"/>
        </placeholder>
      </menu>
    </menu>

    <menu name="Edit" action="EditAction">
      <placeholder name="EditStyleSheetsPlaceholder">
        <menuitem name="EditReportOptions" action="ReportOptionsAction"/>
      </placeholder>
    </menu>

    <menu name="Reports" action="ReportsAction">
      <placeholder name="SavedReportConfigs">
        <menuitem name="ReportSaveConfig" action="ReportSaveAction"/>
        <menuitem name="ReportSaveConfigAs" action="ReportSaveAsAction"/>
      </placeholder>
    </menu>
  </menubar>

  <popup name="MainPopup" action="FakeToplevel">
    <placeholder name="PopupPlaceholder1">
      <menuitem name="PopupOptions" action="ReportOptionsAction"/>
    </placeholder>
  </popup>

  <toolbar name="DefaultToolbar">
    <placeholder name="DefaultToolbarPlaceholder">
      <separator name="ReportToolbarSep0"/>
      <toolitem name="ReportToolbarBack" action="ReportBackAction"/>
      <toolitem name="ReportToolbarForw" action="ReportForwAction"/>
      <toolitem name="ReportToolbarReload" action="ReportReloadAction"/>
      <toolitem name="ReportToolbarStop" action="ReportStopAction"/>
      <separator name="ReportToolbarSep1"/>
      <toolitem name="ReportToolbarOptions" action="ReportOptionsAction"/>
      <toolitem name="ReportToolbarSave" action="ReportSaveAction"/>
      <toolitem name="ReportToolbarSaveAs" action="ReportSaveAsAction"/>
      <toolitem name="ReportToolbarExport" action="ReportExportAction"/>
      <toolitem name="ReportToolbarPrint" action="FilePrintAction" />
      <toolitem name="ReportToolbarExportPDF" action="FilePrintPDFAction"/>
    </placeholder>
  </toolbar>
</ui>
